{
"meta":{"test_sets":[],"test_metrics":[],"learn_metrics":[{"best_value":"Min","name":"RMSE"}],"launch_mode":"Train","parameters":"","iteration_count":100,"learn_sets":["learn"],"name":"experiment"},
"iterations":[
{"learn":[14.005006],"iteration":0,"passed_time":0.001205446062,"remaining_time":0.1193391602},
{"learn":[13.14441192],"iteration":1,"passed_time":0.002198729494,"remaining_time":0.1077377452},
{"learn":[12.34258257],"iteration":2,"passed_time":0.003373436412,"remaining_time":0.109074444},
{"learn":[11.64527793],"iteration":3,"passed_time":0.004101794164,"remaining_time":0.09844305995},
{"learn":[11.02766183],"iteration":4,"passed_time":0.005001345145,"remaining_time":0.09502555776},
{"learn":[10.43485794],"iteration":5,"passed_time":0.005929020871,"remaining_time":0.09288799365},
{"learn":[9.890641275],"iteration":6,"passed_time":0.006844492842,"remaining_time":0.09093397633},
{"learn":[9.492161212],"iteration":7,"passed_time":0.00785540058,"remaining_time":0.09033710667},
{"learn":[9.105082953],"iteration":8,"passed_time":0.008803736175,"remaining_time":0.08901555466},
{"learn":[8.674157135],"iteration":9,"passed_time":0.009649512483,"remaining_time":0.08684561235},
{"learn":[8.341743544],"iteration":10,"passed_time":0.01051646,"remaining_time":0.08508772183},
{"learn":[8.049372916],"iteration":11,"passed_time":0.01135963124,"remaining_time":0.08330396242},
{"learn":[7.757318612],"iteration":12,"passed_time":0.01218507798,"remaining_time":0.08154629106},
{"learn":[7.522206899],"iteration":13,"passed_time":0.01301649634,"remaining_time":0.07995847749},
{"learn":[7.297756655],"iteration":14,"passed_time":0.01385751338,"remaining_time":0.07852590915},
{"learn":[7.088359431],"iteration":15,"passed_time":0.01466145826,"remaining_time":0.07697265588},
{"learn":[6.882113791],"iteration":16,"passed_time":0.0156273387,"remaining_time":0.07629818306},
{"learn":[6.704728832],"iteration":17,"passed_time":0.01678563333,"remaining_time":0.07646788515},
{"learn":[6.563881962],"iteration":18,"passed_time":0.01771475186,"remaining_time":0.07552078425},
{"learn":[6.418790279],"iteration":19,"passed_time":0.0185993838,"remaining_time":0.0743975352},
{"learn":[6.315756953],"iteration":20,"passed_time":0.01975482287,"remaining_time":0.07431576222},
{"learn":[6.210157751],"iteration":21,"passed_time":0.02109080336,"remaining_time":0.07477648465},
{"learn":[6.115058449],"iteration":22,"passed_time":0.02234518502,"remaining_time":0.07480779334},
{"learn":[6.014819884],"iteration":23,"passed_time":0.02364171873,"remaining_time":0.07486544265},
{"learn":[5.93117229],"iteration":24,"passed_time":0.02494320208,"remaining_time":0.07482960623},
{"learn":[5.844857622],"iteration":25,"passed_time":0.02639537875,"remaining_time":0.07512530874},
{"learn":[5.771145213],"iteration":26,"passed_time":0.02765281636,"remaining_time":0.074765022},
{"learn":[5.704018229],"iteration":27,"passed_time":0.02878417856,"remaining_time":0.07401645915},
{"learn":[5.665806474],"iteration":28,"passed_time":0.03021153692,"remaining_time":0.0739661766},
{"learn":[5.616500369],"iteration":29,"passed_time":0.03138771636,"remaining_time":0.07323800484},
{"learn":[5.558023666],"iteration":30,"passed_time":0.0324775878,"remaining_time":0.07228882446},
{"learn":[5.510080976],"iteration":31,"passed_time":0.03362814737,"remaining_time":0.07145981316},
{"learn":[5.468747792],"iteration":32,"passed_time":0.0346259496,"remaining_time":0.0703011704},
{"learn":[5.429275534],"iteration":33,"passed_time":0.03557196101,"remaining_time":0.06905145373},
{"learn":[5.402117324],"iteration":34,"passed_time":0.03643585258,"remaining_time":0.06766658337},
{"learn":[5.367635151],"iteration":35,"passed_time":0.03732420176,"remaining_time":0.06635413646},
{"learn":[5.345181232],"iteration":36,"passed_time":0.03834881583,"remaining_time":0.06529663236},
{"learn":[5.319151269],"iteration":37,"passed_time":0.03934766009,"remaining_time":0.06419881383},
{"learn":[5.296134146],"iteration":38,"passed_time":0.04025475575,"remaining_time":0.06296256669},
{"learn":[5.269629003],"iteration":39,"passed_time":0.04109755627,"remaining_time":0.06164633441},
{"learn":[5.251147059],"iteration":40,"passed_time":0.04197310052,"remaining_time":0.06040031538},
{"learn":[5.248003302],"iteration":41,"passed_time":0.04234393235,"remaining_time":0.05847495419},
{"learn":[5.232376509],"iteration":42,"passed_time":0.04315319759,"remaining_time":0.05720307587},
{"learn":[5.213524255],"iteration":43,"passed_time":0.04412276485,"remaining_time":0.05615624618},
{"learn":[5.189691584],"iteration":44,"passed_time":0.04500086408,"remaining_time":0.0550010561},
{"learn":[5.166052198],"iteration":45,"passed_time":0.04593502242,"remaining_time":0.05392372198},
{"learn":[5.140406659],"iteration":46,"passed_time":0.04679533703,"remaining_time":0.05276920984},
{"learn":[5.118929684],"iteration":47,"passed_time":0.04764943955,"remaining_time":0.05162022618},
{"learn":[5.108792602],"iteration":48,"passed_time":0.04849081729,"remaining_time":0.05047003432},
{"learn":[5.098141225],"iteration":49,"passed_time":0.04949264771,"remaining_time":0.04949264771},
{"learn":[5.085926393],"iteration":50,"passed_time":0.05038699856,"remaining_time":0.04841103784},
{"learn":[5.067816804],"iteration":51,"passed_time":0.05138093326,"remaining_time":0.04742855378},
{"learn":[5.049834901],"iteration":52,"passed_time":0.05242921375,"remaining_time":0.04649383106},
{"learn":[5.03838627],"iteration":53,"passed_time":0.05345180423,"remaining_time":0.04553301841},
{"learn":[5.033534248],"iteration":54,"passed_time":0.05410298175,"remaining_time":0.04426607597},
{"learn":[5.023726885],"iteration":55,"passed_time":0.05498672195,"remaining_time":0.04320385296},
{"learn":[5.01290392],"iteration":56,"passed_time":0.05584774794,"remaining_time":0.04213075722},
{"learn":[5.005569127],"iteration":57,"passed_time":0.05671530665,"remaining_time":0.04106970482},
{"learn":[4.989969032],"iteration":58,"passed_time":0.05777699288,"remaining_time":0.0401501137},
{"learn":[4.976762446],"iteration":59,"passed_time":0.05863832948,"remaining_time":0.03909221965},
{"learn":[4.967222715],"iteration":60,"passed_time":0.05950763158,"remaining_time":0.03804586281},
{"learn":[4.954407599],"iteration":61,"passed_time":0.060344731,"remaining_time":0.03698548029},
{"learn":[4.942125056],"iteration":62,"passed_time":0.06116985711,"remaining_time":0.03592515418},
{"learn":[4.930230716],"iteration":63,"passed_time":0.06201219673,"remaining_time":0.03488186066},
{"learn":[4.921695642],"iteration":64,"passed_time":0.06288551665,"remaining_time":0.03386143204},
{"learn":[4.906405625],"iteration":65,"passed_time":0.06390052271,"remaining_time":0.03291845109},
{"learn":[4.894330248],"iteration":66,"passed_time":0.0648309538,"remaining_time":0.03193166381},
{"learn":[4.88211557],"iteration":67,"passed_time":0.06565729227,"remaining_time":0.03089754931},
{"learn":[4.877946398],"iteration":68,"passed_time":0.06649754784,"remaining_time":0.0298757099},
{"learn":[4.863182126],"iteration":69,"passed_time":0.0674271169,"remaining_time":0.02889733582},
{"learn":[4.84646533],"iteration":70,"passed_time":0.06849354271,"remaining_time":0.02797623575},
{"learn":[4.838014752],"iteration":71,"passed_time":0.06940713101,"remaining_time":0.02699166206},
{"learn":[4.82981137],"iteration":72,"passed_time":0.07025301753,"remaining_time":0.02598399279},
{"learn":[4.817094767],"iteration":73,"passed_time":0.07114919194,"remaining_time":0.02499836474},
{"learn":[4.808314151],"iteration":74,"passed_time":0.07205858207,"remaining_time":0.02401952736},
{"learn":[4.796235023],"iteration":75,"passed_time":0.07300288016,"remaining_time":0.0230535411},
{"learn":[4.784434534],"iteration":76,"passed_time":0.07385496875,"remaining_time":0.02206057508},
{"learn":[4.774402487],"iteration":77,"passed_time":0.07467991451,"remaining_time":0.02106356563},
{"learn":[4.76731896],"iteration":78,"passed_time":0.07551737463,"remaining_time":0.02007423883},
{"learn":[4.75934113],"iteration":79,"passed_time":0.07635661822,"remaining_time":0.01908915456},
{"learn":[4.754106378],"iteration":80,"passed_time":0.07715761737,"remaining_time":0.01809870037},
{"learn":[4.744002932],"iteration":81,"passed_time":0.07799306357,"remaining_time":0.01712042859},
{"learn":[4.731700554],"iteration":82,"passed_time":0.0789377424,"remaining_time":0.01616797133},
{"learn":[4.723284153],"iteration":83,"passed_time":0.07986747212,"remaining_time":0.01521285183},
{"learn":[4.712232782],"iteration":84,"passed_time":0.08095459856,"remaining_time":0.01428610563},
{"learn":[4.703046867],"iteration":85,"passed_time":0.08189038007,"remaining_time":0.0133309921},
{"learn":[4.698601855],"iteration":86,"passed_time":0.08298174441,"remaining_time":0.012399571},
{"learn":[4.692429407],"iteration":87,"passed_time":0.08398465659,"remaining_time":0.01145245317},
{"learn":[4.675027364],"iteration":88,"passed_time":0.08514550757,"remaining_time":0.01052360206},
{"learn":[4.662368584],"iteration":89,"passed_time":0.08623177199,"remaining_time":0.009581307999},
{"learn":[4.646206172],"iteration":90,"passed_time":0.0871053925,"remaining_time":0.008614819038},
{"learn":[4.641245848],"iteration":91,"passed_time":0.08792236273,"remaining_time":0.007645422846},
{"learn":[4.633900435],"iteration":92,"passed_time":0.08877184626,"remaining_time":0.006681751869},
{"learn":[4.624738236],"iteration":93,"passed_time":0.08961565874,"remaining_time":0.00572014843},
{"learn":[4.612798287],"iteration":94,"passed_time":0.09046436075,"remaining_time":0.004761282144},
{"learn":[4.605222001],"iteration":95,"passed_time":0.0913120608,"remaining_time":0.0038046692},
{"learn":[4.601725912],"iteration":96,"passed_time":0.09219428806,"remaining_time":0.002851369734},
{"learn":[4.59722371],"iteration":97,"passed_time":0.09301615783,"remaining_time":0.001898288935},
{"learn":[4.580235665],"iteration":98,"passed_time":0.0941359672,"remaining_time":0.0009508683556},
{"learn":[4.57591791],"iteration":99,"passed_time":0.09524470537,"remaining_time":0}
]}